CoolSelector/__init__.py
coolselector-0.1.0.dist-info/licenses/LICENSE
coolselector-0.1.0.dist-info/METADATA
coolselector-0.1.0.dist-info/WHEEL
coolselector-0.1.0.dist-info/top_level.txt
coolselector-0.1.0.dist-info/RECORD
