Metadata-Version: 2.4
Name: CoolSelector
Version: 0.1.0
Summary: Cool selectors for new python
Author-email: matixandr <u116_matand_waw@technischools.com>
License: MIT
Requires-Python: >=3.13.3
License-File: LICENSE
Dynamic: license-file
